{
  "dev": {
    "awscloudformation": {
      "AuthRoleName": "amplify-siteiot-dev-81006-authRole",
      "UnauthRoleArn": "arn:aws:iam::186384794272:role/amplify-siteiot-dev-81006-unauthRole",
      "AuthRoleArn": "arn:aws:iam::186384794272:role/amplify-siteiot-dev-81006-authRole",
      "Region": "us-east-2",
      "DeploymentBucketName": "amplify-siteiot-dev-81006-deployment",
      "UnauthRoleName": "amplify-siteiot-dev-81006-unauthRole",
      "StackName": "amplify-siteiot-dev-81006",
      "StackId": "arn:aws:cloudformation:us-east-2:186384794272:stack/amplify-siteiot-dev-81006/c6c74e00-f8de-11ea-bc86-021eb120153e",
      "AmplifyAppId": "d3spes8e07g7ke"
    },
    "categories": {
      "auth": {
        "siteiotb6397cdf": {}
      },
      "hosting": {
        "amplifyhosting": {
          "appId": "d3spes8e07g7ke",
          "type": "manual"
        }
      }
    }
  }
}
